setup.py
luggage/__init__.py
luggage/cloudfiles.py
luggage/exceptions.py
luggage/interface.py
luggage/s3.py
luggage/util.py
luggage.egg-info/PKG-INFO
luggage.egg-info/SOURCES.txt
luggage.egg-info/dependency_links.txt
luggage.egg-info/requires.txt
luggage.egg-info/top_level.txt