Metadata-Version: 1.1
Name: luggage
Version: 0.1.2
Summary: A wrapper library for various cloud storage services
Home-page: https://github.com/wonderb0lt/luggage
Author: Patrick Stegmann (aka. @wonderb0lt)
Author-email: code@patrick-stegmann.de
License: UNKNOWN
Platform: UNKNOWN
Classifier: Development Status :: 3 - Alpha
Classifier: License :: OSI Approved :: MIT License
